Kookbook.py
MANIFEST.in
MIT-LICENSE
README.md
boilerpl8.py
setup.py
bin/boilerpl8
boilerpl8.egg-info/PKG-INFO
boilerpl8.egg-info/SOURCES.txt
boilerpl8.egg-info/dependency_links.txt
boilerpl8.egg-info/top_level.txt
tests/boilerpl8_test.py